{
  "item_id": "minecraft:gold_ingot",
  "data": {
    "max_stack_size": 64,
    "translation_key": "item.minecraft.gold_ingot",
    "rarity": "COMMON",
    "fireproof": false,
    "use_animation": "NONE",
    "tags": [
      "minecraft:trim_materials",
      "minecraft:piglin_loved",
      "c:ingots/gold",
      "c:ingots",
      "minecraft:beacon_payment_items",
      "minecraft:gold_tool_materials",
      "minecraft:repairs_gold_armor"
    ],
    "components": {},
    "is_weapon": false,
    "is_food": false
  }
}